measurement_stats/__init__.py
measurement_stats/angle.py
measurement_stats/errors.py
measurement_stats/mean.py
measurement_stats/ops.py
measurement_stats/settings.json
measurement_stats/value2D.py
measurement_stats/values.py
measurement_stats/distributions/__init__.py
measurement_stats/distributions/distributions_ops.py
measurement_stats/distributions/distributions_type.py
measurement_stats/distributions/kernels.py
measurement_stats/distributions/boxes/__init__.py
measurement_stats/distributions/boxes/support.py
measurement_stats/distributions/kernels/__init__.py
measurement_stats/distributions/kernels/gaussians.py
measurement_stats/value/__init__.py
measurement_stats/value/value_ops.py
measurement_stats/value/value_type.py
measurement_stats-0.3.0.dist-info/LICENSE
measurement_stats-0.3.0.dist-info/METADATA
measurement_stats-0.3.0.dist-info/WHEEL
measurement_stats-0.3.0.dist-info/top_level.txt
measurement_stats-0.3.0.dist-info/RECORD
