Metadata-Version: 2.1
Name: measurement-stats
Version: 0.3.0
Summary: Measurement statistics with uncertainties and error propagation
Home-page: https://github.com/sernst/Measurement_Statistics
Author: Scott Ernst
Author-email: swernst@gmail.com
License: MIT
Keywords: measurements statistics uncertainty error propagation
Platform: UNKNOWN
Classifier: Development Status :: 3 - Alpha
Classifier: License :: OSI Approved :: MIT License
Classifier: Programming Language :: Python :: 3
Classifier: Programming Language :: Python :: 3.6
Classifier: Programming Language :: Python :: 3.7
Classifier: Topic :: Scientific/Engineering
Classifier: Topic :: Scientific/Engineering :: Mathematics
Classifier: Topic :: Scientific/Engineering :: Physics
Requires-Dist: pandas
Requires-Dist: numpy
Requires-Dist: six
Requires-Dist: scipy
